saleae/__init__.py
saleae/saleae.py
saleae/version.py
saleae-0.9.1.dist-info/LICENSE.txt
saleae-0.9.1.dist-info/METADATA
saleae-0.9.1.dist-info/WHEEL
saleae-0.9.1.dist-info/top_level.txt
saleae-0.9.1.dist-info/RECORD
